diffacto/__init__.py
diffacto/__main__.py
diffacto/diffacto.py
diffacto-1.0.7.dist-info/LICENSE.txt
diffacto-1.0.7.dist-info/METADATA
diffacto-1.0.7.dist-info/WHEEL
diffacto-1.0.7.dist-info/entry_points.txt
diffacto-1.0.7.dist-info/top_level.txt
diffacto-1.0.7.dist-info/RECORD
