Metadata-Version: 2.1
Name: diffacto
Version: 1.0.7
Summary: A protein summarization method for shotgun proteomics experiments
Home-page: https://github.com/statisticalbiotechnology/diffacto
Author: Bo Zhang, Lukas Käll, KTH
Author-email: lukas.kall@scilifelab.se
Maintainer: Lukas Käll, KTH
Maintainer-email: lukas.kall@scilifelab.se
License: Apache
Classifier: Development Status :: 3 - Alpha
Classifier: Intended Audience :: Developers
Classifier: Topic :: Software Development :: Build Tools
Classifier: License :: OSI Approved :: Apache Software License
Classifier: Programming Language :: Python :: 3
Classifier: Programming Language :: Python :: 3.4
Classifier: Programming Language :: Python :: 3.5
Classifier: Programming Language :: Python :: 3.6
License-File: LICENSE.txt
Requires-Dist: numpy >=1.10
Requires-Dist: scipy >=0.17
Requires-Dist: pandas >=0.18
Requires-Dist: networkx >=1.10
Requires-Dist: scikit-learn >=0.17
Requires-Dist: pyteomics >=3.3
Requires-Dist: Cython >=0.26
